logging_plus/__init__.py
logging_plus-1.1.2.dist-info/LICENSE
logging_plus-1.1.2.dist-info/METADATA
logging_plus-1.1.2.dist-info/WHEEL
logging_plus-1.1.2.dist-info/top_level.txt
logging_plus-1.1.2.dist-info/RECORD
