Metadata-Version: 2.1
Name: logging-plus
Version: 1.1.2
Summary: Add-on for Python logging supporting indentation and generic logging of function entry/exit
Home-page: https://github.com/signag/py-logging-plus
Author: signag
Author-email: siegfried.nagel@t-online.de
Project-URL: Bug Reports, https://github.com/signag/py-logging-plus/issues
Project-URL: Source, https://github.com/signag/py-logging-plus/
Keywords: logging
Classifier: Development Status :: 4 - Beta
Classifier: Intended Audience :: Developers
Classifier: Topic :: Software Development :: Build Tools
Classifier: License :: OSI Approved :: MIT License
Classifier: Programming Language :: Python :: 3
Requires-Python: >=3.6
License-File: LICENSE
Provides-Extra: dev
